{"feed": {
   "xmlns:opensearch": "http://a9.com/-/spec/opensearch/1.1/",
   "link": [
      {
         "rel": "self",
         "type": "application/atom+xml",
         "href": "https://scihub.esa.int/dhus/api/search?q=Cepagatti&start=0&rows=10"
      },
      {
         "rel": "first",
         "type": "application/atom+xml",
         "href": "https://scihub.esa.int/dhus/api/search?q=Cepagatti&start=0&rows=10"
      },
      {
         "rel": "next",
         "type": "application/atom+xml",
         "href": "https://scihub.esa.int/dhus/api/search?q=Cepagatti&start=10&rows=10"
      },
      {
         "rel": "last",
         "type": "application/atom+xml",
         "href": "https://scihub.esa.int/dhus/api/search?q=Cepagatti&start=123&rows=10"
      },
      {
         "rel": "search",
         "type": "application/opensearchdescription+xml",
         "href": "opensearch_description.xml"
      }
   ],
   "xmlns": "http://www.w3.org/2005/Atom",
   "opensearch:itemsPerPage": "10",
   "id": "https://scihub.esa.int/dhus/api/search?q=Cepagatti",
   "author": {"name": "Sentinels Scientific Data Hub"},
   "title": "Sentinels Scientific Data Hub search results for: Cepagatti",
   "updated": "2015-07-19T15:12:44.221Z",
   "opensearch:totalResults": "124",
   "entry": [
      {
         "summary": "Date: 2015-07-17T05:03:09.527Z, Instrument: SAR-C SAR, Mode: VV VH, Satellite: Sentinel-1, Size: 1 GB",
         "id": "2fc4f75e-027c-4896-8a18-d34e35aaeba3",
         "title": "S1A_IW_GRDH_1SDV_20150717T050309_20150717T050334_006846_00939F_E56D",
         "str": [
            {
               "content": "IW",
               "name": "sensoroperationalmode"
            },
            {
               "content": "IW",
               "name": "swathidentifier"
            },
            {
               "content": "DESCENDING",
               "name": "orbitdirection"
            },
            {
               "content": "GRD",
               "name": "producttype"
            },
            {
               "content": "Sentinel-1",
               "name": "platformname"
            },
            {
               "content": "0000-000A",
               "name": "platformidentifier"
            },
            {
               "content": "Synthetic Aperture Radar (C-band)",
               "name": "instrumentname"
            },
            {
               "content": "SAR-C SAR",
               "name": "instrumentshortname"
            },
            {
               "content": "S1A_IW_GRDH_1SDV_20150717T050309_20150717T050334_006846_00939F_E56D.SAFE",
               "name": "filename"
            },
            {
               "content": "SAFE",
               "name": "format"
            },
            {
               "content": "S",
               "name": "productclass"
            },
            {
               "content": "VV VH",
               "name": "polarisationmode"
            },
            {
               "content": "NOMINAL",
               "name": "acquisitiontype"
            },
            {
               "content": "ARCHIVED",
               "name": "status"
            },
            {
               "content": "1 GB",
               "name": "size"
            },
            {
               "content": "<gml:Polygon srsName=\"http://www.opengis.net/gml/srs/epsg.xml#4326\" xmlns:gml=\"http://www.opengis.net/gml\">\n   <gml:outerBoundaryIs>\n      <gml:LinearRing>\n         <gml:coordinates>41.023121,16.985495 41.428757,13.899146 42.928158,14.221872 42.523277,17.381586 41.023121,16.985495<\/gml:coordinates>\n      <\/gml:LinearRing>\n   <\/gml:outerBoundaryIs>\n<\/gml:Polygon>",
               "name": "gmlfootprint"
            },
            {
               "content": "POLYGON ((16.985495 41.023121,13.899146 41.428757,14.221872 42.928158,17.381586 42.523277,16.985495 41.023121))",
               "name": "footprint"
            },
            {
               "content": "S1A_IW_GRDH_1SDV_20150717T050309_20150717T050334_006846_00939F_E56D",
               "name": "identifier"
            }
         ],
         "int": [
            {
               "content": "37791",
               "name": "missiondatatakeid"
            },
            {
               "content": "22",
               "name": "slicenumber"
            },
            {
               "content": "6846",
               "name": "orbitnumber"
            },
            {
               "content": "6846",
               "name": "lastorbitnumber"
            },
            {
               "content": "124",
               "name": "relativeorbitnumber"
            },
            {
               "content": "124",
               "name": "lastrelativeorbitnumber"
            }
         ],
         "link": [
            {"href": "https://scihub.esa.int/dhus/odata/v1/Products('2fc4f75e-027c-4896-8a18-d34e35aaeba3')/$value"},
            {
               "rel": "alternative",
               "href": "https://scihub.esa.int/dhus/odata/v1/Products('2fc4f75e-027c-4896-8a18-d34e35aaeba3')/"
            },
            {
               "rel": "icon",
               "href": "https://scihub.esa.int/dhus/odata/v1/Products('2fc4f75e-027c-4896-8a18-d34e35aaeba3')/Products('Quicklook')/$value"
            }
         ],
         "bool": {
            "content": "true",
            "name": "processed"
         },
         "date": [
            {
               "content": "2015-07-17T05:03:09.527Z",
               "name": "beginposition"
            },
            {
               "content": "2015-07-17T05:03:34.526Z",
               "name": "endposition"
            },
            {
               "content": "2015-07-17T11:10:19.328Z",
               "name": "ingestiondate"
            }
         ]
      },
      {
         "summary": "Date: 2015-07-17T05:03:08.384Z, Instrument: SAR-C SAR, Mode: VV VH, Satellite: Sentinel-1, Size: 7 GB",
         "id": "885f85ab-06b2-41be-9a77-c23c6eb64bd7",
         "title": "S1A_IW_SLC__1SDV_20150717T050308_20150717T050335_006846_00939F_44DE",
         "str": [
            {
               "content": "IW",
               "name": "sensoroperationalmode"
            },
            {
               "content": "IW1 IW2 IW3",
               "name": "swathidentifier"
            },
            {
               "content": "DESCENDING",
               "name": "orbitdirection"
            },
            {
               "content": "SLC",
               "name": "producttype"
            },
            {
               "content": "Sentinel-1",
               "name": "platformname"
            },
            {
               "content": "0000-000A",
               "name": "platformidentifier"
            },
            {
               "content": "Synthetic Aperture Radar (C-band)",
               "name": "instrumentname"
            },
            {
               "content": "SAR-C SAR",
               "name": "instrumentshortname"
            },
            {
               "content": "S1A_IW_SLC__1SDV_20150717T050308_20150717T050335_006846_00939F_44DE.SAFE",
               "name": "filename"
            },
            {
               "content": "SAFE",
               "name": "format"
            },
            {
               "content": "S",
               "name": "productclass"
            },
            {
               "content": "VV VH",
               "name": "polarisationmode"
            },
            {
               "content": "NOMINAL",
               "name": "acquisitiontype"
            },
            {
               "content": "ARCHIVED",
               "name": "status"
            },
            {
               "content": "7 GB",
               "name": "size"
            },
            {
               "content": "<gml:Polygon srsName=\"http://www.opengis.net/gml/srs/epsg.xml#4326\" xmlns:gml=\"http://www.opengis.net/gml\">\n   <gml:outerBoundaryIs>\n      <gml:LinearRing>\n         <gml:coordinates>40.972042,16.975922 41.371189,13.948217 42.990261,14.291528 42.591644,17.399851 40.972042,16.975922<\/gml:coordinates>\n      <\/gml:LinearRing>\n   <\/gml:outerBoundaryIs>\n<\/gml:Polygon>",
               "name": "gmlfootprint"
            },
            {
               "content": "POLYGON ((16.975922 40.972042,13.948217 41.371189,14.291528 42.990261,17.399851 42.591644,16.975922 40.972042))",
               "name": "footprint"
            },
            {
               "content": "S1A_IW_SLC__1SDV_20150717T050308_20150717T050335_006846_00939F_44DE",
               "name": "identifier"
            }
         ],
         "int": [
            {
               "content": "37791",
               "name": "missiondatatakeid"
            },
            {
               "content": "22",
               "name": "slicenumber"
            },
            {
               "content": "6846",
               "name": "orbitnumber"
            },
            {
               "content": "6846",
               "name": "lastorbitnumber"
            },
            {
               "content": "124",
               "name": "relativeorbitnumber"
            },
            {
               "content": "124",
               "name": "lastrelativeorbitnumber"
            }
         ],
         "link": [
            {"href": "https://scihub.esa.int/dhus/odata/v1/Products('885f85ab-06b2-41be-9a77-c23c6eb64bd7')/$value"},
            {
               "rel": "alternative",
               "href": "https://scihub.esa.int/dhus/odata/v1/Products('885f85ab-06b2-41be-9a77-c23c6eb64bd7')/"
            },
            {
               "rel": "icon",
               "href": "https://scihub.esa.int/dhus/odata/v1/Products('885f85ab-06b2-41be-9a77-c23c6eb64bd7')/Products('Quicklook')/$value"
            }
         ],
         "bool": {
            "content": "true",
            "name": "processed"
         },
         "date": [
            {
               "content": "2015-07-17T05:03:08.384Z",
               "name": "beginposition"
            },
            {
               "content": "2015-07-17T05:03:35.365Z",
               "name": "endposition"
            },
            {
               "content": "2015-07-17T10:36:14.499Z",
               "name": "ingestiondate"
            }
         ]
      },
      {
         "summary": "Date: 2015-07-11T16:57:16.991Z, Instrument: SAR-C SAR, Mode: VV VH, Satellite: Sentinel-1, Size: 7 GB",
         "id": "bd2d87d1-8b1b-4473-bb8f-271fc9bf5b9e",
         "title": "S1A_IW_SLC__1SDV_20150711T165716_20150711T165744_006766_009148_ABAC",
         "str": [
            {
               "content": "IW",
               "name": "sensoroperationalmode"
            },
            {
               "content": "IW1 IW2 IW3",
               "name": "swathidentifier"
            },
            {
               "content": "ASCENDING",
               "name": "orbitdirection"
            },
            {
               "content": "SLC",
               "name": "producttype"
            },
            {
               "content": "Sentinel-1",
               "name": "platformname"
            },
            {
               "content": "0000-000A",
               "name": "platformidentifier"
            },
            {
               "content": "Synthetic Aperture Radar (C-band)",
               "name": "instrumentname"
            },
            {
               "content": "SAR-C SAR",
               "name": "instrumentshortname"
            },
            {
               "content": "S1A_IW_SLC__1SDV_20150711T165716_20150711T165744_006766_009148_ABAC.SAFE",
               "name": "filename"
            },
            {
               "content": "SAFE",
               "name": "format"
            },
            {
               "content": "S",
               "name": "productclass"
            },
            {
               "content": "VV VH",
               "name": "polarisationmode"
            },
            {
               "content": "NOMINAL",
               "name": "acquisitiontype"
            },
            {
               "content": "ARCHIVED",
               "name": "status"
            },
            {
               "content": "7 GB",
               "name": "size"
            },
            {
               "content": "<gml:Polygon srsName=\"http://www.opengis.net/gml/srs/epsg.xml#4326\" xmlns:gml=\"http://www.opengis.net/gml\">\n   <gml:outerBoundaryIs>\n      <gml:LinearRing>\n         <gml:coordinates>43.300320,12.546288 43.694752,15.653634 42.019669,16.012697 41.624908,12.990623 43.300320,12.546288<\/gml:coordinates>\n      <\/gml:LinearRing>\n   <\/gml:outerBoundaryIs>\n<\/gml:Polygon>",
               "name": "gmlfootprint"
            },
            {
               "content": "POLYGON ((12.546288 43.300320,15.653634 43.694752,16.012697 42.019669,12.990623 41.624908,12.546288 43.300320))",
               "name": "footprint"
            },
            {
               "content": "S1A_IW_SLC__1SDV_20150711T165716_20150711T165744_006766_009148_ABAC",
               "name": "identifier"
            }
         ],
         "int": [
            {
               "content": "37192",
               "name": "missiondatatakeid"
            },
            {
               "content": "8",
               "name": "slicenumber"
            },
            {
               "content": "6766",
               "name": "orbitnumber"
            },
            {
               "content": "6766",
               "name": "lastorbitnumber"
            },
            {
               "content": "44",
               "name": "relativeorbitnumber"
            },
            {
               "content": "44",
               "name": "lastrelativeorbitnumber"
            }
         ],
         "link": [
            {"href": "https://scihub.esa.int/dhus/odata/v1/Products('bd2d87d1-8b1b-4473-bb8f-271fc9bf5b9e')/$value"},
            {
               "rel": "alternative",
               "href": "https://scihub.esa.int/dhus/odata/v1/Products('bd2d87d1-8b1b-4473-bb8f-271fc9bf5b9e')/"
            },
            {
               "rel": "icon",
               "href": "https://scihub.esa.int/dhus/odata/v1/Products('bd2d87d1-8b1b-4473-bb8f-271fc9bf5b9e')/Products('Quicklook')/$value"
            }
         ],
         "bool": {
            "content": "true",
            "name": "processed"
         },
         "date": [
            {
               "content": "2015-07-11T16:57:16.991Z",
               "name": "beginposition"
            },
            {
               "content": "2015-07-11T16:57:44.91Z",
               "name": "endposition"
            },
            {
               "content": "2015-07-12T00:28:04.212Z",
               "name": "ingestiondate"
            }
         ]
      },
      {
         "summary": "Date: 2015-07-11T16:57:18.436Z, Instrument: SAR-C SAR, Mode: VV VH, Satellite: Sentinel-1, Size: 1 GB",
         "id": "12717fcb-d7a2-42b5-aa2e-09f6dc214c01",
         "title": "S1A_IW_GRDH_1SDV_20150711T165718_20150711T165743_006766_009148_AE84",
         "str": [
            {
               "content": "IW",
               "name": "sensoroperationalmode"
            },
            {
               "content": "IW",
               "name": "swathidentifier"
            },
            {
               "content": "ASCENDING",
               "name": "orbitdirection"
            },
            {
               "content": "GRD",
               "name": "producttype"
            },
            {
               "content": "Sentinel-1",
               "name": "platformname"
            },
            {
               "content": "0000-000A",
               "name": "platformidentifier"
            },
            {
               "content": "Synthetic Aperture Radar (C-band)",
               "name": "instrumentname"
            },
            {
               "content": "SAR-C SAR",
               "name": "instrumentshortname"
            },
            {
               "content": "S1A_IW_GRDH_1SDV_20150711T165718_20150711T165743_006766_009148_AE84.SAFE",
               "name": "filename"
            },
            {
               "content": "SAFE",
               "name": "format"
            },
            {
               "content": "S",
               "name": "productclass"
            },
            {
               "content": "VV VH",
               "name": "polarisationmode"
            },
            {
               "content": "NOMINAL",
               "name": "acquisitiontype"
            },
            {
               "content": "ARCHIVED",
               "name": "status"
            },
            {
               "content": "1 GB",
               "name": "size"
            },
            {
               "content": "<gml:Polygon srsName=\"http://www.opengis.net/gml/srs/epsg.xml#4326\" xmlns:gml=\"http://www.opengis.net/gml\">\n   <gml:outerBoundaryIs>\n      <gml:LinearRing>\n         <gml:coordinates>43.210648,12.562900 43.607376,15.684023 42.109280,16.020500 41.712292,12.973475 43.210648,12.562900<\/gml:coordinates>\n      <\/gml:LinearRing>\n   <\/gml:outerBoundaryIs>\n<\/gml:Polygon>",
               "name": "gmlfootprint"
            },
            {
               "content": "POLYGON ((12.562900 43.210648,15.684023 43.607376,16.020500 42.109280,12.973475 41.712292,12.562900 43.210648))",
               "name": "footprint"
            },
            {
               "content": "S1A_IW_GRDH_1SDV_20150711T165718_20150711T165743_006766_009148_AE84",
               "name": "identifier"
            }
         ],
         "int": [
            {
               "content": "37192",
               "name": "missiondatatakeid"
            },
            {
               "content": "8",
               "name": "slicenumber"
            },
            {
               "content": "6766",
               "name": "orbitnumber"
            },
            {
               "content": "6766",
               "name": "lastorbitnumber"
            },
            {
               "content": "44",
               "name": "relativeorbitnumber"
            },
            {
               "content": "44",
               "name": "lastrelativeorbitnumber"
            }
         ],
         "link": [
            {"href": "https://scihub.esa.int/dhus/odata/v1/Products('12717fcb-d7a2-42b5-aa2e-09f6dc214c01')/$value"},
            {
               "rel": "alternative",
               "href": "https://scihub.esa.int/dhus/odata/v1/Products('12717fcb-d7a2-42b5-aa2e-09f6dc214c01')/"
            },
            {
               "rel": "icon",
               "href": "https://scihub.esa.int/dhus/odata/v1/Products('12717fcb-d7a2-42b5-aa2e-09f6dc214c01')/Products('Quicklook')/$value"
            }
         ],
         "bool": {
            "content": "true",
            "name": "processed"
         },
         "date": [
            {
               "content": "2015-07-11T16:57:18.436Z",
               "name": "beginposition"
            },
            {
               "content": "2015-07-11T16:57:43.435Z",
               "name": "endposition"
            },
            {
               "content": "2015-07-11T23:16:04.975Z",
               "name": "ingestiondate"
            }
         ]
      },
      {
         "summary": "Date: 2015-07-11T16:57:14.852Z, Instrument: SAR-C SAR, Mode: VH VV, Satellite: Sentinel-1, Size: 1 GB",
         "id": "732e7162-6404-4bc1-9a55-598485d481fe",
         "title": "S1A_IW_RAW__0SDV_20150711T165714_20150711T165747_006766_009148_A029",
         "str": [
            {
               "content": "RAW",
               "name": "producttype"
            },
            {
               "content": "IW",
               "name": "sensoroperationalmode"
            },
            {
               "content": "ASCENDING",
               "name": "orbitdirection"
            },
            {
               "content": "SLICE",
               "name": "productconsolidation"
            },
            {
               "content": "Sentinel-1",
               "name": "platformname"
            },
            {
               "content": "0000-000A",
               "name": "platformidentifier"
            },
            {
               "content": "Synthetic Aperture Radar (C-band)",
               "name": "instrumentname"
            },
            {
               "content": "SAR-C SAR",
               "name": "instrumentshortname"
            },
            {
               "content": "S1A_IW_RAW__0SDV_20150711T165714_20150711T165747_006766_009148_A029.SAFE",
               "name": "filename"
            },
            {
               "content": "SAFE",
               "name": "format"
            },
            {
               "content": "S",
               "name": "productclass"
            },
            {
               "content": "VH VV",
               "name": "polarisationmode"
            },
            {
               "content": "NOMINAL",
               "name": "acquisitiontype"
            },
            {
               "content": "ARCHIVED",
               "name": "status"
            },
            {
               "content": "1 GB",
               "name": "size"
            },
            {
               "content": "<gml:Polygon srsName=\"http://www.opengis.net/gml/srs/epsg.xml#4326\" xmlns:gml=\"http://www.opengis.net/gml\">\n   <gml:outerBoundaryIs>\n      <gml:LinearRing>\n         <gml:coordinates>41.6031,15.8908 43.5564,15.4773 43.2796,12.4540 41.3290,12.9614 41.6031,15.8908 41.6031,15.8908<\/gml:coordinates>\n      <\/gml:LinearRing>\n   <\/gml:outerBoundaryIs>\n<\/gml:Polygon>",
               "name": "gmlfootprint"
            },
            {
               "content": "POLYGON ((15.8908 41.6031,15.4773 43.5564,12.4540 43.2796,12.9614 41.3290,15.8908 41.6031,15.8908 41.6031))",
               "name": "footprint"
            },
            {
               "content": "S1A_IW_RAW__0SDV_20150711T165714_20150711T165747_006766_009148_A029",
               "name": "identifier"
            }
         ],
         "int": [
            {
               "content": "37192",
               "name": "missiondatatakeid"
            },
            {
               "content": "8",
               "name": "slicenumber"
            },
            {
               "content": "6766",
               "name": "orbitnumber"
            },
            {
               "content": "6766",
               "name": "lastorbitnumber"
            },
            {
               "content": "44",
               "name": "relativeorbitnumber"
            },
            {
               "content": "44",
               "name": "lastrelativeorbitnumber"
            }
         ],
         "link": [
            {"href": "https://scihub.esa.int/dhus/odata/v1/Products('732e7162-6404-4bc1-9a55-598485d481fe')/$value"},
            {
               "rel": "alternative",
               "href": "https://scihub.esa.int/dhus/odata/v1/Products('732e7162-6404-4bc1-9a55-598485d481fe')/"
            },
            {
               "rel": "icon",
               "href": "https://scihub.esa.int/dhus/odata/v1/Products('732e7162-6404-4bc1-9a55-598485d481fe')/Products('Quicklook')/$value"
            }
         ],
         "bool": {
            "content": "true",
            "name": "processed"
         },
         "date": [
            {
               "content": "2015-07-11T16:57:14.852Z",
               "name": "beginposition"
            },
            {
               "content": "2015-07-11T16:57:47.252Z",
               "name": "endposition"
            },
            {
               "content": "2015-07-11T20:50:04.658Z",
               "name": "ingestiondate"
            }
         ]
      },
      {
         "summary": "Date: 2015-07-10T05:11:15.87Z, Instrument: SAR-C SAR, Mode: VV VH, Satellite: Sentinel-1, Size: 7 GB",
         "id": "51627b06-b840-4773-925e-050cd7aa3160",
         "title": "S1A_IW_SLC__1SDV_20150710T051115_20150710T051142_006744_00909D_3C42",
         "str": [
            {
               "content": "IW",
               "name": "sensoroperationalmode"
            },
            {
               "content": "IW1 IW2 IW3",
               "name": "swathidentifier"
            },
            {
               "content": "DESCENDING",
               "name": "orbitdirection"
            },
            {
               "content": "SLC",
               "name": "producttype"
            },
            {
               "content": "Sentinel-1",
               "name": "platformname"
            },
            {
               "content": "0000-000A",
               "name": "platformidentifier"
            },
            {
               "content": "Synthetic Aperture Radar (C-band)",
               "name": "instrumentname"
            },
            {
               "content": "SAR-C SAR",
               "name": "instrumentshortname"
            },
            {
               "content": "S1A_IW_SLC__1SDV_20150710T051115_20150710T051142_006744_00909D_3C42.SAFE",
               "name": "filename"
            },
            {
               "content": "SAFE",
               "name": "format"
            },
            {
               "content": "S",
               "name": "productclass"
            },
            {
               "content": "VV VH",
               "name": "polarisationmode"
            },
            {
               "content": "NOMINAL",
               "name": "acquisitiontype"
            },
            {
               "content": "ARCHIVED",
               "name": "status"
            },
            {
               "content": "7 GB",
               "name": "size"
            },
            {
               "content": "<gml:Polygon srsName=\"http://www.opengis.net/gml/srs/epsg.xml#4326\" xmlns:gml=\"http://www.opengis.net/gml\">\n   <gml:outerBoundaryIs>\n      <gml:LinearRing>\n         <gml:coordinates>41.307358,14.999010 41.702248,11.989116 43.320568,12.334274 42.926109,15.425200 41.307358,14.999010<\/gml:coordinates>\n      <\/gml:LinearRing>\n   <\/gml:outerBoundaryIs>\n<\/gml:Polygon>",
               "name": "gmlfootprint"
            },
            {
               "content": "POLYGON ((14.999010 41.307358,11.989116 41.702248,12.334274 43.320568,15.425200 42.926109,14.999010 41.307358))",
               "name": "footprint"
            },
            {
               "content": "S1A_IW_SLC__1SDV_20150710T051115_20150710T051142_006744_00909D_3C42",
               "name": "identifier"
            }
         ],
         "int": [
            {
               "content": "37021",
               "name": "missiondatatakeid"
            },
            {
               "content": "10",
               "name": "slicenumber"
            },
            {
               "content": "6744",
               "name": "orbitnumber"
            },
            {
               "content": "6744",
               "name": "lastorbitnumber"
            },
            {
               "content": "22",
               "name": "relativeorbitnumber"
            },
            {
               "content": "22",
               "name": "lastrelativeorbitnumber"
            }
         ],
         "link": [
            {"href": "https://scihub.esa.int/dhus/odata/v1/Products('51627b06-b840-4773-925e-050cd7aa3160')/$value"},
            {
               "rel": "alternative",
               "href": "https://scihub.esa.int/dhus/odata/v1/Products('51627b06-b840-4773-925e-050cd7aa3160')/"
            },
            {
               "rel": "icon",
               "href": "https://scihub.esa.int/dhus/odata/v1/Products('51627b06-b840-4773-925e-050cd7aa3160')/Products('Quicklook')/$value"
            }
         ],
         "bool": {
            "content": "true",
            "name": "processed"
         },
         "date": [
            {
               "content": "2015-07-10T05:11:15.87Z",
               "name": "beginposition"
            },
            {
               "content": "2015-07-10T05:11:42.841Z",
               "name": "endposition"
            },
            {
               "content": "2015-07-10T14:18:04.865Z",
               "name": "ingestiondate"
            }
         ]
      },
      {
         "summary": "Date: 2015-07-10T05:11:13.133Z, Instrument: SAR-C SAR, Mode: VH VV, Satellite: Sentinel-1, Size: 1 GB",
         "id": "e6d6c1a9-afe1-4753-bdcb-a7e5f6eab9df",
         "title": "S1A_IW_RAW__0SDV_20150710T051113_20150710T051145_006744_00909D_C1DD",
         "str": [
            {
               "content": "RAW",
               "name": "producttype"
            },
            {
               "content": "IW",
               "name": "sensoroperationalmode"
            },
            {
               "content": "DESCENDING",
               "name": "orbitdirection"
            },
            {
               "content": "SLICE",
               "name": "productconsolidation"
            },
            {
               "content": "Sentinel-1",
               "name": "platformname"
            },
            {
               "content": "0000-000A",
               "name": "platformidentifier"
            },
            {
               "content": "Synthetic Aperture Radar (C-band)",
               "name": "instrumentname"
            },
            {
               "content": "SAR-C SAR",
               "name": "instrumentshortname"
            },
            {
               "content": "S1A_IW_RAW__0SDV_20150710T051113_20150710T051145_006744_00909D_C1DD.SAFE",
               "name": "filename"
            },
            {
               "content": "SAFE",
               "name": "format"
            },
            {
               "content": "S",
               "name": "productclass"
            },
            {
               "content": "VH VV",
               "name": "polarisationmode"
            },
            {
               "content": "NOMINAL",
               "name": "acquisitiontype"
            },
            {
               "content": "ARCHIVED",
               "name": "status"
            },
            {
               "content": "1 GB",
               "name": "size"
            },
            {
               "content": "<gml:Polygon srsName=\"http://www.opengis.net/gml/srs/epsg.xml#4326\" xmlns:gml=\"http://www.opengis.net/gml\">\n   <gml:outerBoundaryIs>\n      <gml:LinearRing>\n         <gml:coordinates>43.2049,12.5316 41.2515,12.1197 40.9779,15.0340 42.9287,15.5381 43.2049,12.5316 43.2049,12.5316<\/gml:coordinates>\n      <\/gml:LinearRing>\n   <\/gml:outerBoundaryIs>\n<\/gml:Polygon>",
               "name": "gmlfootprint"
            },
            {
               "content": "POLYGON ((12.5316 43.2049,12.1197 41.2515,15.0340 40.9779,15.5381 42.9287,12.5316 43.2049,12.5316 43.2049))",
               "name": "footprint"
            },
            {
               "content": "S1A_IW_RAW__0SDV_20150710T051113_20150710T051145_006744_00909D_C1DD",
               "name": "identifier"
            }
         ],
         "int": [
            {
               "content": "37021",
               "name": "missiondatatakeid"
            },
            {
               "content": "10",
               "name": "slicenumber"
            },
            {
               "content": "6744",
               "name": "orbitnumber"
            },
            {
               "content": "6744",
               "name": "lastorbitnumber"
            },
            {
               "content": "22",
               "name": "relativeorbitnumber"
            },
            {
               "content": "22",
               "name": "lastrelativeorbitnumber"
            }
         ],
         "link": [
            {"href": "https://scihub.esa.int/dhus/odata/v1/Products('e6d6c1a9-afe1-4753-bdcb-a7e5f6eab9df')/$value"},
            {
               "rel": "alternative",
               "href": "https://scihub.esa.int/dhus/odata/v1/Products('e6d6c1a9-afe1-4753-bdcb-a7e5f6eab9df')/"
            },
            {
               "rel": "icon",
               "href": "https://scihub.esa.int/dhus/odata/v1/Products('e6d6c1a9-afe1-4753-bdcb-a7e5f6eab9df')/Products('Quicklook')/$value"
            }
         ],
         "bool": {
            "content": "true",
            "name": "processed"
         },
         "date": [
            {
               "content": "2015-07-10T05:11:13.133Z",
               "name": "beginposition"
            },
            {
               "content": "2015-07-10T05:11:45.533Z",
               "name": "endposition"
            },
            {
               "content": "2015-07-10T13:04:06.834Z",
               "name": "ingestiondate"
            }
         ]
      },
      {
         "summary": "Date: 2015-07-10T05:11:16.715Z, Instrument: SAR-C SAR, Mode: VV VH, Satellite: Sentinel-1, Size: 1 GB",
         "id": "32060d6e-0136-42bd-bc80-1c1d6633552f",
         "title": "S1A_IW_GRDH_1SDV_20150710T051116_20150710T051141_006744_00909D_13D3",
         "str": [
            {
               "content": "IW",
               "name": "sensoroperationalmode"
            },
            {
               "content": "IW",
               "name": "swathidentifier"
            },
            {
               "content": "DESCENDING",
               "name": "orbitdirection"
            },
            {
               "content": "GRD",
               "name": "producttype"
            },
            {
               "content": "Sentinel-1",
               "name": "platformname"
            },
            {
               "content": "0000-000A",
               "name": "platformidentifier"
            },
            {
               "content": "Synthetic Aperture Radar (C-band)",
               "name": "instrumentname"
            },
            {
               "content": "SAR-C SAR",
               "name": "instrumentshortname"
            },
            {
               "content": "S1A_IW_GRDH_1SDV_20150710T051116_20150710T051141_006744_00909D_13D3.SAFE",
               "name": "filename"
            },
            {
               "content": "SAFE",
               "name": "format"
            },
            {
               "content": "S",
               "name": "productclass"
            },
            {
               "content": "VV VH",
               "name": "polarisationmode"
            },
            {
               "content": "NOMINAL",
               "name": "acquisitiontype"
            },
            {
               "content": "ARCHIVED",
               "name": "status"
            },
            {
               "content": "1 GB",
               "name": "size"
            },
            {
               "content": "<gml:Polygon srsName=\"http://www.opengis.net/gml/srs/epsg.xml#4326\" xmlns:gml=\"http://www.opengis.net/gml\">\n   <gml:outerBoundaryIs>\n      <gml:LinearRing>\n         <gml:coordinates>41.376560,15.007168 41.774677,11.963949 43.272858,12.298665 42.875057,15.415438 41.376560,15.007168<\/gml:coordinates>\n      <\/gml:LinearRing>\n   <\/gml:outerBoundaryIs>\n<\/gml:Polygon>",
               "name": "gmlfootprint"
            },
            {
               "content": "POLYGON ((15.007168 41.376560,11.963949 41.774677,12.298665 43.272858,15.415438 42.875057,15.007168 41.376560))",
               "name": "footprint"
            },
            {
               "content": "S1A_IW_GRDH_1SDV_20150710T051116_20150710T051141_006744_00909D_13D3",
               "name": "identifier"
            }
         ],
         "int": [
            {
               "content": "37021",
               "name": "missiondatatakeid"
            },
            {
               "content": "10",
               "name": "slicenumber"
            },
            {
               "content": "6744",
               "name": "orbitnumber"
            },
            {
               "content": "6744",
               "name": "lastorbitnumber"
            },
            {
               "content": "22",
               "name": "relativeorbitnumber"
            },
            {
               "content": "22",
               "name": "lastrelativeorbitnumber"
            }
         ],
         "link": [
            {"href": "https://scihub.esa.int/dhus/odata/v1/Products('32060d6e-0136-42bd-bc80-1c1d6633552f')/$value"},
            {
               "rel": "alternative",
               "href": "https://scihub.esa.int/dhus/odata/v1/Products('32060d6e-0136-42bd-bc80-1c1d6633552f')/"
            },
            {
               "rel": "icon",
               "href": "https://scihub.esa.int/dhus/odata/v1/Products('32060d6e-0136-42bd-bc80-1c1d6633552f')/Products('Quicklook')/$value"
            }
         ],
         "bool": {
            "content": "true",
            "name": "processed"
         },
         "date": [
            {
               "content": "2015-07-10T05:11:16.715Z",
               "name": "beginposition"
            },
            {
               "content": "2015-07-10T05:11:41.714Z",
               "name": "endposition"
            },
            {
               "content": "2015-07-10T12:36:04.351Z",
               "name": "ingestiondate"
            }
         ]
      },
      {
         "summary": "Date: 2015-06-29T16:57:06.584Z, Instrument: SAR-C SAR, Mode: VV VH, Satellite: Sentinel-1, Size: 7 GB",
         "id": "f7649125-03cb-43b7-9269-2e0a3eac291d",
         "title": "S1A_IW_SLC__1SDV_20150629T165706_20150629T165734_006591_008C79_30CE",
         "str": [
            {
               "content": "IW",
               "name": "sensoroperationalmode"
            },
            {
               "content": "IW1 IW2 IW3",
               "name": "swathidentifier"
            },
            {
               "content": "ASCENDING",
               "name": "orbitdirection"
            },
            {
               "content": "SLC",
               "name": "producttype"
            },
            {
               "content": "Sentinel-1",
               "name": "platformname"
            },
            {
               "content": "0000-000A",
               "name": "platformidentifier"
            },
            {
               "content": "Synthetic Aperture Radar (C-band)",
               "name": "instrumentname"
            },
            {
               "content": "SAR-C SAR",
               "name": "instrumentshortname"
            },
            {
               "content": "S1A_IW_SLC__1SDV_20150629T165706_20150629T165734_006591_008C79_30CE.SAFE",
               "name": "filename"
            },
            {
               "content": "SAFE",
               "name": "format"
            },
            {
               "content": "S",
               "name": "productclass"
            },
            {
               "content": "VV VH",
               "name": "polarisationmode"
            },
            {
               "content": "NOMINAL",
               "name": "acquisitiontype"
            },
            {
               "content": "ARCHIVED",
               "name": "status"
            },
            {
               "content": "7 GB",
               "name": "size"
            },
            {
               "content": "<gml:Polygon srsName=\"http://www.opengis.net/gml/srs/epsg.xml#4326\" xmlns:gml=\"http://www.opengis.net/gml\">\n   <gml:outerBoundaryIs>\n      <gml:LinearRing>\n         <gml:coordinates>42.638348,12.728178 43.032726,15.801566 41.357079,16.157934 40.962193,13.167076 42.638348,12.728178<\/gml:coordinates>\n      <\/gml:LinearRing>\n   <\/gml:outerBoundaryIs>\n<\/gml:Polygon>",
               "name": "gmlfootprint"
            },
            {
               "content": "POLYGON ((12.728178 42.638348,15.801566 43.032726,16.157934 41.357079,13.167076 40.962193,12.728178 42.638348))",
               "name": "footprint"
            },
            {
               "content": "S1A_IW_SLC__1SDV_20150629T165706_20150629T165734_006591_008C79_30CE",
               "name": "identifier"
            }
         ],
         "int": [
            {
               "content": "35961",
               "name": "missiondatatakeid"
            },
            {
               "content": "8",
               "name": "slicenumber"
            },
            {
               "content": "6591",
               "name": "orbitnumber"
            },
            {
               "content": "6591",
               "name": "lastorbitnumber"
            },
            {
               "content": "44",
               "name": "relativeorbitnumber"
            },
            {
               "content": "44",
               "name": "lastrelativeorbitnumber"
            }
         ],
         "link": [
            {"href": "https://scihub.esa.int/dhus/odata/v1/Products('f7649125-03cb-43b7-9269-2e0a3eac291d')/$value"},
            {
               "rel": "alternative",
               "href": "https://scihub.esa.int/dhus/odata/v1/Products('f7649125-03cb-43b7-9269-2e0a3eac291d')/"
            },
            {
               "rel": "icon",
               "href": "https://scihub.esa.int/dhus/odata/v1/Products('f7649125-03cb-43b7-9269-2e0a3eac291d')/Products('Quicklook')/$value"
            }
         ],
         "bool": {
            "content": "true",
            "name": "processed"
         },
         "date": [
            {
               "content": "2015-06-29T16:57:06.584Z",
               "name": "beginposition"
            },
            {
               "content": "2015-06-29T16:57:34.506Z",
               "name": "endposition"
            },
            {
               "content": "2015-06-30T00:18:37.819Z",
               "name": "ingestiondate"
            }
         ]
      },
      {
         "summary": "Date: 2015-06-29T16:57:29.464Z, Instrument: SAR-C SAR, Mode: VH VV, Satellite: Sentinel-1, Size: 1 GB",
         "id": "a046a3dc-7020-43eb-8c1e-018cd7c7f8e0",
         "title": "S1A_IW_RAW__0SDV_20150629T165729_20150629T165801_006591_008C79_B221",
         "str": [
            {
               "content": "RAW",
               "name": "producttype"
            },
            {
               "content": "IW",
               "name": "sensoroperationalmode"
            },
            {
               "content": "ASCENDING",
               "name": "orbitdirection"
            },
            {
               "content": "SLICE",
               "name": "productconsolidation"
            },
            {
               "content": "Sentinel-1",
               "name": "platformname"
            },
            {
               "content": "0000-000A",
               "name": "platformidentifier"
            },
            {
               "content": "Synthetic Aperture Radar (C-band)",
               "name": "instrumentname"
            },
            {
               "content": "SAR-C SAR",
               "name": "instrumentshortname"
            },
            {
               "content": "S1A_IW_RAW__0SDV_20150629T165729_20150629T165801_006591_008C79_B221.SAFE",
               "name": "filename"
            },
            {
               "content": "SAFE",
               "name": "format"
            },
            {
               "content": "S",
               "name": "productclass"
            },
            {
               "content": "VH VV",
               "name": "polarisationmode"
            },
            {
               "content": "NOMINAL",
               "name": "acquisitiontype"
            },
            {
               "content": "ARCHIVED",
               "name": "status"
            },
            {
               "content": "1 GB",
               "name": "size"
            },
            {
               "content": "<gml:Polygon srsName=\"http://www.opengis.net/gml/srs/epsg.xml#4326\" xmlns:gml=\"http://www.opengis.net/gml\">\n   <gml:outerBoundaryIs>\n      <gml:LinearRing>\n         <gml:coordinates>42.4455,15.7084 44.3985,15.2911 44.1203,12.2244 42.1703,12.7396 42.4455,15.7084 42.4455,15.7084<\/gml:coordinates>\n      <\/gml:LinearRing>\n   <\/gml:outerBoundaryIs>\n<\/gml:Polygon>",
               "name": "gmlfootprint"
            },
            {
               "content": "POLYGON ((15.7084 42.4455,15.2911 44.3985,12.2244 44.1203,12.7396 42.1703,15.7084 42.4455,15.7084 42.4455))",
               "name": "footprint"
            },
            {
               "content": "S1A_IW_RAW__0SDV_20150629T165729_20150629T165801_006591_008C79_B221",
               "name": "identifier"
            }
         ],
         "int": [
            {
               "content": "35961",
               "name": "missiondatatakeid"
            },
            {
               "content": "9",
               "name": "slicenumber"
            },
            {
               "content": "6591",
               "name": "orbitnumber"
            },
            {
               "content": "6591",
               "name": "lastorbitnumber"
            },
            {
               "content": "44",
               "name": "relativeorbitnumber"
            },
            {
               "content": "44",
               "name": "lastrelativeorbitnumber"
            }
         ],
         "link": [
            {"href": "https://scihub.esa.int/dhus/odata/v1/Products('a046a3dc-7020-43eb-8c1e-018cd7c7f8e0')/$value"},
            {
               "rel": "alternative",
               "href": "https://scihub.esa.int/dhus/odata/v1/Products('a046a3dc-7020-43eb-8c1e-018cd7c7f8e0')/"
            },
            {
               "rel": "icon",
               "href": "https://scihub.esa.int/dhus/odata/v1/Products('a046a3dc-7020-43eb-8c1e-018cd7c7f8e0')/Products('Quicklook')/$value"
            }
         ],
         "bool": {
            "content": "true",
            "name": "processed"
         },
         "date": [
            {
               "content": "2015-06-29T16:57:29.464Z",
               "name": "beginposition"
            },
            {
               "content": "2015-06-29T16:58:01.864Z",
               "name": "endposition"
            },
            {
               "content": "2015-06-29T23:04:46.947Z",
               "name": "ingestiondate"
            }
         ]
      }
   ],
   "subtitle": "Displaying 0 to 9 of 124 total results. Request done in 0.041 seconds.",
   "opensearch:startIndex": "0",
   "opensearch:Query": {
      "searchTerms": "Cepagatti",
      "role": "request",
      "startPage": "1"
   }
}}